  1           0 LOAD_CONST               0 (3)
              2 STORE_NAME               0 (a)

  2           4 LOAD_CONST               1 (5)
              6 STORE_NAME               1 (b)

  3           8 LOAD_CONST               2 (9202)
             10 STORE_NAME               2 (c)

  4          12 SETUP_LOOP              32 (to 46)
        >>   14 LOAD_NAME                0 (a)
             16 LOAD_NAME                1 (b)
             18 COMPARE_OP               0 (<)
             20 POP_JUMP_IF_FALSE       44

  5          22 LOAD_NAME                3 (print)
             24 LOAD_NAME                0 (a)
             26 LOAD_NAME                1 (b)
             28 BINARY_ADD
             30 CALL_FUNCTION            1
             32 POP_TOP

  6          34 LOAD_NAME                0 (a)
             36 LOAD_CONST               3 (1)
             38 INPLACE_ADD
             40 STORE_NAME               0 (a)
             42 JUMP_ABSOLUTE           14
        >>   44 POP_BLOCK
        >>   46 LOAD_CONST               4 (None)
             48 RETURN_VALUE
