  1           0 LOAD_CONST               0 (3)
              2 STORE_NAME               0 (a)

  2           4 LOAD_CONST               1 ('b')
              6 STORE_NAME               1 (b)

  3           8 LOAD_CONST               2 (0)
             10 STORE_NAME               2 (c)

  4          12 LOAD_CONST              10 (-23)
             14 STORE_NAME               3 (d)

  5          16 LOAD_CONST              11 (-0.6)
             18 STORE_NAME               4 (e)

  6          20 LOAD_CONST               5 ('d')
             22 STORE_NAME               5 (f)

  7          24 LOAD_CONST               6 (3.2)
             26 STORE_NAME               6 (g)

  8          28 LOAD_CONST               7 ('')
             30 STORE_NAME               7 (h)

  9          32 LOAD_CONST               8 ('This is a String')
             34 STORE_NAME               8 (i)
             36 LOAD_CONST               9 (None)
             38 RETURN_VALUE
